pdf/__init__.py
pdffile/__init__.py
pdffile-0.0.4.dist-info/LICENSE
pdffile-0.0.4.dist-info/METADATA
pdffile-0.0.4.dist-info/WHEEL
pdffile-0.0.4.dist-info/top_level.txt
pdffile-0.0.4.dist-info/RECORD
