Metadata-Version: 2.1
Name: pdffile
Version: 0.0.4
Summary: A modern pure-python library for reading PDF files
Home-page: https://github.com/py-pdf/pdf
Author: Martin Thoma
Author-email: info@martin-thoma.de
Maintainer: Martin Thoma
Maintainer-email: info@martin-thoma.de
License: BSD
Project-URL: Changelog, https://github.com/py-pdf/pdf/blob/main/CHANGELOG.md
Keywords: PDF
Platform: UNKNOWN
Classifier: Development Status :: 1 - Planning
Classifier: Intended Audience :: Developers
Classifier: License :: OSI Approved :: BSD License
Classifier: Operating System :: OS Independent
Classifier: Programming Language :: Python :: 3
Classifier: Programming Language :: Python :: 3 :: Only
Classifier: Programming Language :: Python :: 3.7
Classifier: Programming Language :: Python :: 3.8
Classifier: Programming Language :: Python :: 3.9
Classifier: Programming Language :: Python :: 3.10
Classifier: Topic :: Software Development
Requires-Python: >=3.7.0
License-File: LICENSE
Requires-Dist: PyPDF2
